README.rst
setup.cfg
setup.py
cadccutout/__init__.py
cadccutout/core.py
cadccutout/cutoutnd.py
cadccutout/file_helper.py
cadccutout/no_content_error.py
cadccutout/pixel_cutout_hdu.py
cadccutout/pixel_range_input_parser.py
cadccutout/shape.py
cadccutout/transform.py
cadccutout/utils.py
cadccutout/version.py
cadccutout.egg-info/PKG-INFO
cadccutout.egg-info/SOURCES.txt
cadccutout.egg-info/dependency_links.txt
cadccutout.egg-info/entry_points.txt
cadccutout.egg-info/not-zip-safe
cadccutout.egg-info/requires.txt
cadccutout.egg-info/top_level.txt
cadccutout/file_helpers/__init__.py
cadccutout/file_helpers/base_file_helper.py
cadccutout/file_helpers/fits/__init__.py
cadccutout/file_helpers/fits/fits_file_helper.py