Metadata-Version: 1.1
Name: cadccutout
Version: 0.3.1
Summary: Cutout library in Python
Home-page: http://www.cadc-ccda.hia-iha.nrc-cnrc.gc.ca/
Author: Canadian Astronomy Data Centre
Author-email: cadc@nrc-cnrc.gc.ca
License: AGPLv3
Platform: UNKNOWN
Classifier: Natural Language :: English
Classifier: License :: OSI Approved :: GNU Affero General Public License v3
Classifier: Programming Language :: Python
Classifier: Programming Language :: Python :: 2.7
Classifier: Programming Language :: Python :: 3.5
Classifier: Programming Language :: Python :: 3.6
Classifier: Programming Language :: Python :: 3.7
